Metadata-Version: 1.1
Name: asciifolder
Version: 0.1.0
Summary: pretty print folder structure to cli
Home-page: https://github.com/danielhrisca/asciifolder
Author: Daniel Hrisca
Author-email: daniel.hrisca@gmail.com
License: MIT
Keywords: ascii folder structure
Platform: UNKNOWN
Classifier: Development Status :: 4 - Beta
Classifier: Intended Audience :: Developers
Classifier: Topic :: Software Development
Classifier: License :: OSI Approved :: MIT License
Classifier: Programming Language :: Python :: 2.7
Classifier: Programming Language :: Python :: 3.4
Classifier: Programming Language :: Python :: 3.5
Classifier: Programming Language :: Python :: 3.6
Classifier: Programming Language :: Python :: 3.7
